{
  "project_info": {
    "project_number": "853506835440",
    "firebase_url": "https://reservenow-2020.firebaseio.com",
    "project_id": "reservenow-2020",
    "storage_bucket": "reservenow-2020.appspot.com"
  },
  "client": [
    {
      "client_info": {
        "mobilesdk_app_id": "1:853506835440:android:5505346b49f4ace3719335",
        "android_client_info": {
          "package_name": "com.projectmoviles.myapplication"
        }
      },
      "oauth_client": [
        {
          "client_id": "853506835440-rl84kgpofp4hd14u1nd8844ud42gbkei.apps.googleusercontent.com",
          "client_type": 3
        }
      ],
      "api_key": [
        {
          "current_key": "AIzaSyD16YBQ0DGiylCKmE4ZyzwsD9uU8GVqIuA"
        }
      ],
      "services": {
        "appinvite_service": {
          "other_platform_oauth_client": [
            {
              "client_id": "853506835440-rl84kgpofp4hd14u1nd8844ud42gbkei.apps.googleusercontent.com",
              "client_type": 3
            }
          ]
        }
      }
    }
  ],
  "configuration_version": "1"
}